qdeep/__init__.py
qdeep/dqn/__init__.py
qdeep/dqn/agent.py
qdeep/dqn/learning.py
qdeep/env_wrappers/__init__.py
qdeep/env_wrappers/gym_wrapper.py
qdeep/utils/__init__.py
qdeep/utils/env_loop.py
qdeep/utils/utils.py
qdeep/utils/visualization.py
qdeep-0.0.1.dist-info/LICENSE
qdeep-0.0.1.dist-info/METADATA
qdeep-0.0.1.dist-info/WHEEL
qdeep-0.0.1.dist-info/top_level.txt
qdeep-0.0.1.dist-info/RECORD
